annax/__init__.py
annax/index.py
annax/ivf.py
annax/kmeans.py
annax/ops.py
annax/pfunc.py
annax/pq.py
annax/search.py
annax/serialize.py
annax/version.py
annax-0.0.1.dist-info/LICENSE
annax-0.0.1.dist-info/METADATA
annax-0.0.1.dist-info/WHEEL
annax-0.0.1.dist-info/top_level.txt
annax-0.0.1.dist-info/RECORD
