Metadata-Version: 2.1
Name: annax
Version: 0.0.1
Summary: Fast and memory-efficient approximate nearest neighbor search with JAX
Home-page: https://github.com/atksh/annax
Author: atksh
License: MIT License
Requires-Python: >=3.7
License-File: LICENSE
Requires-Dist: jax (>=0.4.8)
Requires-Dist: jaxlib (>=0.4.7)
Requires-Dist: numpy (>=1.24.2)
Requires-Dist: zstandard (~=0.20.0)
Provides-Extra: dev
Requires-Dist: pytest (~=7.2.2) ; extra == 'dev'
Requires-Dist: black (~=23.3.0) ; extra == 'dev'
Requires-Dist: isort (~=5.12.0) ; extra == 'dev'
Requires-Dist: pre-commit (~=3.2.2) ; extra == 'dev'
